[
  {
    "layer": 0, 
    "path": "london.bg/sky.png", 
    "x": 0, 
    "y": 0
  }, 
  {
    "layer": 1, 
    "path": "london.bg/cloud_01.png", 
    "x": 683, 
    "y": 72
  }, 
  {
    "layer": 1, 
    "path": "london.bg/cloud_02.png", 
    "x": 771, 
    "y": 43
  }, 
  {
    "layer": 1, 
    "path": "london.bg/cloud_03.png", 
    "x": 633, 
    "y": 80
  }, 
  {
    "layer": 1, 
    "path": "london.bg/cloud_04.png", 
    "x": -291, 
    "y": 72
  }, 
  {
    "layer": 1, 
    "path": "london.bg/cloud_05.png", 
    "x": 810, 
    "y": 90
  }, 
  {
    "layer": 1, 
    "path": "london.bg/cloud_06.png", 
    "x": 333, 
    "y": 30
  }, 
  {
    "layer": 1, 
    "path": "london.bg/cloud_07.png", 
    "x": 78, 
    "y": -10
  }, 
  {
    "layer": 1, 
    "path": "london.bg/cloud_08.png", 
    "type": "skip", 
    "x": -512, 
    "y": 60
  }, 
  {
    "layer": 2, 
    "path": "london.bg/viveska.png", 
    "type": "skip", 
    "x": 1304, 
    "y": 88
  }, 
  {
    "layer": 2, 
    "path": "london.bg/plane.png", 
    "type": "skip", 
    "x": 1252, 
    "y": 88
  }, 
  {
    "layer": 2, 
    "path": "london.bg/bg.png", 
    "x": 0, 
    "y": 0
  }, 
  {
    "layer": 30, 
    "path": "london.bg/balloon_01.png", 
    "x": 206, 
    "y": 7
  }, 
  {
    "layer": 30, 
    "path": "london.bg/balloon_02.png", 
    "x": 577, 
    "y": 233
  }, 
  {
    "layer": 30, 
    "path": "london.bg/balloon_03.png", 
    "x": 950, 
    "y": 148
  }, 
  {
    "layer": 30, 
    "path": "london.bg/balloon_04.png", 
    "x": 1097, 
    "y": 53
  }, 
  {
    "layer": 30, 
    "path": "london.bg/balloon_01_cover.png", 
    "x": 243, 
    "y": 150
  }, 
  {
    "layer": 30, 
    "path": "london.bg/balloon_02_cover.png", 
    "x": 599, 
    "y": 316
  }, 
  {
    "layer": 30, 
    "path": "london.bg/balloon_03_cover.png", 
    "x": 980, 
    "y": 237
  }, 
  {
    "layer": 30, 
    "path": "london.bg/balloon_04_cover.png", 
    "x": 1145, 
    "y": 187
  }
]
