[
  {
    "layer": 3, 
    "path": "garden.bg/bg.png", 
    "x": 0, 
    "y": 0
  }, 
  {
    "layer": 6, 
    "path": "garden.bg/glow1.png", 
    "type": "effect", 
    "x": 1064, 
    "y": 239
  }, 
  {
    "layer": 6, 
    "path": "garden.bg/glow2.png", 
    "type": "effect", 
    "x": 881, 
    "y": 251
  }, 
  {
    "layer": 6, 
    "path": "garden.bg/glow3.png", 
    "type": "effect", 
    "x": 413, 
    "y": 257
  }, 
  {
    "layer": 6, 
    "path": "garden.bg/glow4.png", 
    "type": "effect", 
    "x": 228, 
    "y": 233
  }
]
